{"cameraMode":{"drawMode":0,"name":"Shaded","section":"Shading Mode"},"sceneLighting":true,"audioPlay":false,"sceneViewState":{"m_AlwaysRefresh":false,"showFog":true,"showSkybox":true,"showFlares":true,"showImageEffects":true,"showParticleSystems":true,"showVisualEffectGraphs":true,"m_FxEnabled":true},"in2DMode":false,"pivot":{"x":-46.30131530761719,"y":-15.368525505065918,"z":39.41912078857422},"rotation":{"x":0.13971254229545594,"y":-0.4494595229625702,"z":0.07134178280830383,"w":0.8794705271720886},"size":35.377525329589847,"orthographic":false}